hepml/__init__.py
hepml/_nbdev.py
hepml/core.py
hepml/evaluation.py
hepml/structured.py
hepml-0.0.12.dist-info/LICENSE
hepml-0.0.12.dist-info/METADATA
hepml-0.0.12.dist-info/WHEEL
hepml-0.0.12.dist-info/entry_points.txt
hepml-0.0.12.dist-info/top_level.txt
hepml-0.0.12.dist-info/RECORD
