Metadata-Version: 2.1
Name: hepml
Version: 0.0.12
Summary: Practical machine learning for particle physicists
Home-page: https://github.com/lewtun/hepml
Author: Lewis Tunstall
Author-email: lewis.c.tunstall@gmail.com
License: Apache Software License 2.0
Keywords: machine learning
Platform: UNKNOWN
Classifier: Development Status :: 3 - Alpha
Classifier: Intended Audience :: Developers
Classifier: License :: OSI Approved :: Apache Software License
Classifier: Natural Language :: English
Classifier: Programming Language :: Python :: 3.6
Classifier: Programming Language :: Python :: 3.7
Classifier: Programming Language :: Python :: 3.8
Requires-Python: >=3.6
Requires-Dist: scikit-learn
Requires-Dist: pandas
Requires-Dist: numpy
Requires-Dist: seaborn
Requires-Dist: black
Requires-Dist: tqdm
Requires-Dist: wget
Requires-Dist: nbdev
Requires-Dist: sklearn-pandas
Requires-Dist: graphviz
Requires-Dist: gdown
Requires-Dist: pyarrow
Requires-Dist: numba
Requires-Dist: Cython
Requires-Dist: fastprogress
Requires-Dist: giotto-tda
Requires-Dist: pillow
